xdwlib/.annotatable.py.swp
xdwlib/.annotation.py.swp
xdwlib/.basedocument.py.swp
xdwlib/.binder.py.swp
xdwlib/.documentinbinder.py.swp
xdwlib/.xdwapi.py.swp
xdwlib/__init__.py
xdwlib/__setup__.py
xdwlib/annotatable.py
xdwlib/annotation.py
xdwlib/basedocument.py
xdwlib/binder.py
xdwlib/bitmap.py
xdwlib/common.py
xdwlib/document.py
xdwlib/documentinbinder.py
xdwlib/observer.py
xdwlib/page.py
xdwlib/struct.py
xdwlib/timezone.py
xdwlib/xdwapi.py
xdwlib/xdwfile.py
xdwlib/xdwtemp.py
xdwlib-3.9.7.data/scripts/xdw2text.py
xdwlib-3.9.7.dist-info/LICENSE.rst
xdwlib-3.9.7.dist-info/METADATA
xdwlib-3.9.7.dist-info/WHEEL
xdwlib-3.9.7.dist-info/top_level.txt
xdwlib-3.9.7.dist-info/RECORD
