Metadata-Version: 2.1
Name: xdwlib
Version: 3.9.7
Summary: A DocuWorks library.
Home-page: https://github.com/hayasix/xdwlib
Author: HAYASHI Hideki
Author-email: hideki@hayasix.com
License: UNKNOWN
Platform: win32
Classifier: Development Status :: 4 - Beta
Classifier: Environment :: Console
Classifier: Intended Audience :: End Users/Desktop
Classifier: Intended Audience :: Developers
Classifier: License :: OSI Approved :: Zope Public License
Classifier: Operating System :: Microsoft :: Windows
Classifier: Programming Language :: Python
Classifier: Programming Language :: Python :: 3
Classifier: Programming Language :: Python :: 3.7
Classifier: Programming Language :: Python :: 3.8
Classifier: Programming Language :: Python :: 3.9
Classifier: Topic :: Office/Business
Classifier: Topic :: Documentation
Requires-Python: >=3.7
